LICENSE.txt
README.md
setup.cfg
setup.py
pySEP/__init__.py
pySEP/buses.py
pySEP/circuito.py
pySEP/fluxo.py
pySEP/gui.py
pySEP/jcb.py
pySEP/lines.py
pySEP/plotagem.py
pySEP/run.py
pySEP.egg-info/PKG-INFO
pySEP.egg-info/SOURCES.txt
pySEP.egg-info/dependency_links.txt
pySEP.egg-info/top_level.txt
pySEP/images/logo_pySEP.ico
pySEP/images/pySEP_logo.png