Metadata-Version: 2.1
Name: pySEP
Version: 1.0.9
Summary: Pacote Open Source desenvolvido no Brasil para modelar e simular Sistemas Elétricos de Potência. Open Source Package developed in Brazil to model and simulate Electric Power Systems
Home-page: https://github.com/mrcsantos1/pySEP
Author: Marcos Alves dos Santos
Author-email: mrcsantos1@outlook.com
License: Apache License
Project-URL: Source Code, https://github.com/mrcsantos1/pySEP
Project-URL: Download, https://github.com/mrcsantos1/pySEP/archive/master.zip
Keywords: Load Flow,Power Flow,Newton-Raphson,Fluxo de Potência,Python,Electrical Engineering,Engenharia Elétrica
Platform: UNKNOWN
Classifier: Development Status :: 6 - Mature
Classifier: Environment :: Console
Classifier: Framework :: Matplotlib
Classifier: Intended Audience :: Education
Classifier: Intended Audience :: Science/Research
Classifier: Intended Audience :: Science/Research
Classifier: License :: OSI Approved :: Apache Software License
Classifier: Natural Language :: Portuguese (Brazilian)
Classifier: Operating System :: OS Independent
Classifier: Programming Language :: Python :: 3 :: Only
Classifier: Programming Language :: Python :: 3.0
Classifier: Programming Language :: Python :: 3.1
Classifier: Programming Language :: Python :: 3.2
Classifier: Programming Language :: Python :: 3.3
Classifier: Programming Language :: Python :: 3.4
Classifier: Programming Language :: Python :: 3.5
Classifier: Programming Language :: Python :: 3.6
Classifier: Programming Language :: Python :: 3.7
Classifier: Programming Language :: Python :: 3.8
Classifier: Programming Language :: Python :: 3.9
Classifier: Topic :: Adaptive Technologies
Classifier: Topic :: Education
Classifier: Topic :: Education :: Computer Aided Instruction (CAI)
Classifier: Topic :: Education :: Testing
Classifier: Topic :: Scientific/Engineering
Classifier: Topic :: Scientific/Engineering :: Electronic Design Automation (EDA)
Classifier: Topic :: Scientific/Engineering :: GIS
Classifier: Topic :: Scientific/Engineering :: Information Analysis
Classifier: Topic :: Scientific/Engineering :: Interface Engine/Protocol Translator
Classifier: Topic :: Scientific/Engineering :: Mathematics
Classifier: Topic :: Scientific/Engineering :: Visualization
Classifier: Topic :: Scientific/Engineering :: Physics
Classifier: Topic :: Software Development :: Libraries
Classifier: Topic :: Software Development :: Libraries :: Python Modules
Classifier: Topic :: Utilities
